MANIFEST.in
README
setup.cfg
setup.py
django_notifyAll.egg-info/PKG-INFO
django_notifyAll.egg-info/SOURCES.txt
django_notifyAll.egg-info/dependency_links.txt
django_notifyAll.egg-info/requires.txt
django_notifyAll.egg-info/top_level.txt
notifyAll/__init__.py
notifyAll/models.py
notifyAll/tests.py
notifyAll/config/__init__.py
notifyAll/config/email_provider_settings.py
notifyAll/config/local.py
notifyAll/config/settings.py
notifyAll/config/sms_provider_settings.py
notifyAll/config/urls.py
notifyAll/config/wsgi.py
notifyAll/providers/__init__.py
notifyAll/providers/base.py
notifyAll/providers/gmail/__init__.py
notifyAll/providers/gmail/provider.py
notifyAll/providers/plivo/__init__.py
notifyAll/providers/plivo/provider.py
notifyAll/providers/sendgrid/__init__.py
notifyAll/providers/sendgrid/provider.py
notifyAll/providers/twilio/__init__.py
notifyAll/providers/twilio/provider.py
notifyAll/services/__init__.py
notifyAll/services/notifier.py
notifyAll/services/service_config.py