Metadata-Version: 1.1
Name: django-notifyAll
Version: 0.3
Summary: A lib which you can use for all types of notifications like SMS, Mail, Push.
Home-page: https://github.com/inforian/django-notifyAll
Author: Neeraj Dhiman
Author-email: ndhiman08@gmail.com
License: GPL
Download-URL: https://github.com/inforian/django-notifyAll/archive/v0.3.tar.gz
Keywords: notification,notify,sms,email,push
Platform: UNKNOWN
